example_package/__init__.py
example_package/test_utils.py
pip_test_HongyanWang-0.0.1.dist-info/LICENCE
pip_test_HongyanWang-0.0.1.dist-info/METADATA
pip_test_HongyanWang-0.0.1.dist-info/WHEEL
pip_test_HongyanWang-0.0.1.dist-info/top_level.txt
pip_test_HongyanWang-0.0.1.dist-info/RECORD
