Metadata-Version: 2.1
Name: pip-test-HongyanWang
Version: 0.0.1
Summary: first test pip 
Home-page: https://github.com/pypa/sampleproject
Author: HongyanWang
Author-email: author@example.com
License: UNKNOWN
Project-URL: Bug Tracker, https://github.com/pypa/sampleproject/issues
Platform: UNKNOWN
Classifier: Programming Language :: Python :: 3
Classifier: License :: OSI Approved :: MIT License
Classifier: Operating System :: OS Independent
Requires-Python: >=3.6
License-File: LICENCE
